i3smartfocus/__init__.py
i3smartfocus/i3smartfocus.py
i3smartfocus-0.1.4.dist-info/LICENSE
i3smartfocus-0.1.4.dist-info/METADATA
i3smartfocus-0.1.4.dist-info/WHEEL
i3smartfocus-0.1.4.dist-info/entry_points.txt
i3smartfocus-0.1.4.dist-info/top_level.txt
i3smartfocus-0.1.4.dist-info/RECORD
