Metadata-Version: 2.1
Name: i3smartfocus
Version: 0.1.4
Summary: i3wm smart focus
Home-page: https://github.com/deadc0de6/i3smartfocus
Author: deadc0de6
Author-email: deadc0de6@foo.bar
License: GPLv3
Download-URL: https://github.com/deadc0de6/i3smartfocus/archive/v0.1.4.tar.gz
Keywords: i3wm tiling focus
Platform: UNKNOWN
Classifier: Development Status :: 5 - Production/Stable
Classifier: Programming Language :: Python :: 3.6
Classifier: Programming Language :: Python :: 3.7
Classifier: Programming Language :: Python :: 3.8
Classifier: Programming Language :: Python :: 3.9
Classifier: Programming Language :: Python :: 3.10
Classifier: License :: OSI Approved :: GNU General Public License v3 (GPLv3)
Requires-Python: >=3.4
Requires-Dist: i3ipc
Provides-Extra: dev
Requires-Dist: check-manifest ; extra == 'dev'
Provides-Extra: test
Requires-Dist: pycodestyle ; extra == 'test'
Requires-Dist: pyflakes ; extra == 'test'
